.gitignore
LICENSE
README.md
entry_points.txt
ocupgrader-example.yml
requirements.txt
setup.cfg
setup.py
ocupgrader/__init__.py
ocupgrader/main.py
ocupgrader/schema.py
ocupgrader.egg-info/PKG-INFO
ocupgrader.egg-info/SOURCES.txt
ocupgrader.egg-info/dependency_links.txt
ocupgrader.egg-info/entry_points.txt
ocupgrader.egg-info/top_level.txt