Metadata-Version: 2.1
Name: ocupgrader
Version: 0.1.0
Summary: A tool which wraps the OpenShift command line tools to make upgrades easier
Home-page: https://www.github.com/jdobes/ocupgrader
Author: Jan Dobes
Author-email: jdobes@redhat.com
License: MIT
Keywords: openshift,kubernetes
Platform: UNKNOWN
Classifier: Topic :: Utilities
Classifier: License :: OSI Approved :: MIT License
Classifier: Programming Language :: Python
Classifier: Programming Language :: Python :: 3
Classifier: Programming Language :: Python :: 3.4
Classifier: Programming Language :: Python :: 3.5
Classifier: Programming Language :: Python :: 3.6
Requires-Python: >=3.4
